gxcutil/__init__.py
gxcutil/aes.py
gxcutil/base58.py
gxcutil/client.py
gxcutil/hash.py
gxcutil/key.py
gxcutil/serialize.py
gxcutil/utils.py
gxcutil/ecc/__init__.py
gxcutil/ecc/curve.py
gxcutil/ecc/ecdsa.py
gxcutil/ecc/point.py
gxcutil/ecc/secp256k1.py
gxcutil-0.1.18.dist-info/LICENSE
gxcutil-0.1.18.dist-info/METADATA
gxcutil-0.1.18.dist-info/WHEEL
gxcutil-0.1.18.dist-info/top_level.txt
gxcutil-0.1.18.dist-info/RECORD
