Metadata-Version: 2.1
Name: gxcutil
Version: 0.1.18
Summary: Python utility library for GXC
Home-page: https://github.com/Game-X-Coin/gxcutil
Author: Lucid
Author-email: contact@lucid.dev
License: UNKNOWN
Platform: UNKNOWN
Requires-Dist: pycrypto (==2.6.1)
